[
  {
    "timestamp": "2026-04-10T11:15:41Z",
    "timestamp_local": "2026-04-10 18:15:41",
    "station": "DKI19 Pondok Rangon",
    "ispu": "58",
    "parameter": "PM25",
    "tanggal": "04/10/2026 18:00:00"
  },
  {
    "timestamp": "2026-04-10T11:15:41Z",
    "timestamp_local": "2026-04-10 18:15:41",
    "station": "DKI16 Ancol",
    "ispu": "29",
    "parameter": "PM25",
    "tanggal": "04/10/2026 18:00:00"
  },
  {
    "timestamp": "2026-04-10T11:15:41Z",
    "timestamp_local": "2026-04-10 18:15:41",
    "station": "DKI17 SDN 07 Kramat Pela",
    "ispu": "3451",
    "parameter": "PM25",
    "tanggal": "04/10/2026 17:00:00"
  },
  {
    "timestamp": "2026-04-10T11:15:41Z",
    "timestamp_local": "2026-04-10 18:15:41",
    "station": "DKI20 Rusunawa Pesakih",
    "ispu": "50",
    "parameter": "PM25",
    "tanggal": "04/10/2026 18:00:00"
  },
  {
    "timestamp": "2026-04-10T11:15:41Z",
    "timestamp_local": "2026-04-10 18:15:41",
    "station": "DKI18 Lebak Bulus",
    "ispu": "53",
    "parameter": "PM25",
    "tanggal": "04/10/2026 18:00:00"
  },
  {
    "timestamp": "2026-04-10T11:15:41Z",
    "timestamp_local": "2026-04-10 18:15:41",
    "station": "DKI13 TMB Gombol Paya, Kalideres",
    "ispu": "56",
    "parameter": "PM25",
    "tanggal": "03/26/2026 19:30:00"
  },
  {
    "timestamp": "2026-04-10T11:15:41Z",
    "timestamp_local": "2026-04-10 18:15:41",
    "station": "DKI06 RPTRA Manggala Bisma, Papanggo",
    "ispu": "110",
    "parameter": "SO2",
    "tanggal": "04/02/2026 10:00:00"
  },
  {
    "timestamp": "2026-04-10T11:15:41Z",
    "timestamp_local": "2026-04-10 18:15:41",
    "station": "DKI96 Taman Sungai Kendal",
    "ispu": "32",
    "parameter": "PM25",
    "tanggal": "04/10/2026 18:00:00"
  },
  {
    "timestamp": "2026-04-10T11:15:41Z",
    "timestamp_local": "2026-04-10 18:15:41",
    "station": "DKI11 Jakarta Equestrian Pulomas",
    "ispu": "42",
    "parameter": "CO",
    "tanggal": "04/10/2026 18:00:00"
  }
]