[
  {
    "timestamp": "2026-04-14T14:15:42Z",
    "timestamp_local": "2026-04-14 21:15:42",
    "station": "DKI19 Pondok Rangon",
    "ispu": "68",
    "parameter": "PM25",
    "tanggal": "04/14/2026 21:00:00"
  },
  {
    "timestamp": "2026-04-14T14:15:42Z",
    "timestamp_local": "2026-04-14 21:15:42",
    "station": "DKI16 Ancol",
    "ispu": "61",
    "parameter": "PM25",
    "tanggal": "04/14/2026 21:00:00"
  },
  {
    "timestamp": "2026-04-14T14:15:42Z",
    "timestamp_local": "2026-04-14 21:15:42",
    "station": "DKI17 SDN 07 Kramat Pela",
    "ispu": "64",
    "parameter": "PM25",
    "tanggal": "04/14/2026 21:00:00"
  },
  {
    "timestamp": "2026-04-14T14:15:42Z",
    "timestamp_local": "2026-04-14 21:15:42",
    "station": "DKI20 Rusunawa Pesakih",
    "ispu": "68",
    "parameter": "PM25",
    "tanggal": "04/14/2026 21:00:00"
  },
  {
    "timestamp": "2026-04-14T14:15:42Z",
    "timestamp_local": "2026-04-14 21:15:42",
    "station": "DKI13 TMB Gombol Paya, Kalideres",
    "ispu": "56",
    "parameter": "PM25",
    "tanggal": "03/26/2026 19:30:00"
  },
  {
    "timestamp": "2026-04-14T14:15:42Z",
    "timestamp_local": "2026-04-14 21:15:42",
    "station": "DKI06 RPTRA Manggala Bisma, Papanggo",
    "ispu": "97",
    "parameter": "SO2",
    "tanggal": "04/14/2026 21:00:00"
  },
  {
    "timestamp": "2026-04-14T14:15:42Z",
    "timestamp_local": "2026-04-14 21:15:42",
    "station": "DKI95 Tebet Eco Park",
    "ispu": "63",
    "parameter": "PM25",
    "tanggal": "04/14/2026 21:00:00"
  },
  {
    "timestamp": "2026-04-14T14:15:42Z",
    "timestamp_local": "2026-04-14 21:15:42",
    "station": "DKI96 Taman Sungai Kendal",
    "ispu": "60",
    "parameter": "PM25",
    "tanggal": "04/14/2026 21:00:00"
  },
  {
    "timestamp": "2026-04-14T14:15:42Z",
    "timestamp_local": "2026-04-14 21:15:42",
    "station": "DKI08 PPOP Ragunan",
    "ispu": "0",
    "parameter": "SO2",
    "tanggal": "04/14/2026 21:00:00"
  }
]