[
  {
    "timestamp": "2026-04-13T21:45:39Z",
    "timestamp_local": "2026-04-14 04:45:39",
    "station": "DKI19 Pondok Rangon",
    "ispu": "83",
    "parameter": "PM25",
    "tanggal": "04/14/2026 04:30:00"
  },
  {
    "timestamp": "2026-04-13T21:45:39Z",
    "timestamp_local": "2026-04-14 04:45:39",
    "station": "DKI16 Ancol",
    "ispu": "69",
    "parameter": "PM25",
    "tanggal": "04/14/2026 04:30:00"
  },
  {
    "timestamp": "2026-04-13T21:45:39Z",
    "timestamp_local": "2026-04-14 04:45:39",
    "station": "DKI20 Rusunawa Pesakih",
    "ispu": "71",
    "parameter": "PM25",
    "tanggal": "04/14/2026 04:30:00"
  },
  {
    "timestamp": "2026-04-13T21:45:39Z",
    "timestamp_local": "2026-04-14 04:45:39",
    "station": "DKI13 TMB Gombol Paya, Kalideres",
    "ispu": "56",
    "parameter": "PM25",
    "tanggal": "03/26/2026 19:30:00"
  },
  {
    "timestamp": "2026-04-13T21:45:39Z",
    "timestamp_local": "2026-04-14 04:45:39",
    "station": "DKI06 RPTRA Manggala Bisma, Papanggo",
    "ispu": "102",
    "parameter": "PM25",
    "tanggal": "04/14/2026 04:30:00"
  },
  {
    "timestamp": "2026-04-13T21:45:39Z",
    "timestamp_local": "2026-04-14 04:45:39",
    "station": "DKI05 Kebun Jeruk",
    "ispu": "80",
    "parameter": "PM25",
    "tanggal": "04/14/2026 04:00:00"
  },
  {
    "timestamp": "2026-04-13T21:45:39Z",
    "timestamp_local": "2026-04-14 04:45:39",
    "station": "DKI03 Jagakarsa",
    "ispu": "60",
    "parameter": "PM25",
    "tanggal": "04/14/2026 04:00:00"
  },
  {
    "timestamp": "2026-04-13T21:45:39Z",
    "timestamp_local": "2026-04-14 04:45:39",
    "station": "DKI02 Kelapa Gading",
    "ispu": "78",
    "parameter": "PM25",
    "tanggal": "04/14/2026 04:00:00"
  },
  {
    "timestamp": "2026-04-13T21:45:39Z",
    "timestamp_local": "2026-04-14 04:45:39",
    "station": "DKI95 Tebet Eco Park",
    "ispu": "73",
    "parameter": "PM25",
    "tanggal": "04/14/2026 04:30:00"
  },
  {
    "timestamp": "2026-04-13T21:45:39Z",
    "timestamp_local": "2026-04-14 04:45:39",
    "station": "DKI96 Taman Sungai Kendal",
    "ispu": "70",
    "parameter": "PM25",
    "tanggal": "04/14/2026 04:30:00"
  },
  {
    "timestamp": "2026-04-13T21:45:39Z",
    "timestamp_local": "2026-04-14 04:45:39",
    "station": "DKI04 Lubang Buaya",
    "ispu": "93",
    "parameter": "PM25",
    "tanggal": "04/14/2026 04:00:00"
  },
  {
    "timestamp": "2026-04-13T21:45:39Z",
    "timestamp_local": "2026-04-14 04:45:39",
    "station": "DKI01 Bundaran HI",
    "ispu": "93",
    "parameter": "PM25",
    "tanggal": "04/14/2026 04:00:00"
  }
]