[
  {
    "timestamp": "2026-04-30T13:15:14Z",
    "timestamp_local": "2026-04-30 20:15:14",
    "station": "DKI19 Pondok Rangon",
    "ispu": "91",
    "parameter": "PM25",
    "tanggal": "04/30/2026 20:00:00"
  },
  {
    "timestamp": "2026-04-30T13:15:14Z",
    "timestamp_local": "2026-04-30 20:15:14",
    "station": "DKI12 GOR Cendrawasih",
    "ispu": "189",
    "parameter": "SO2",
    "tanggal": "04/30/2026 20:00:00"
  },
  {
    "timestamp": "2026-04-30T13:15:14Z",
    "timestamp_local": "2026-04-30 20:15:14",
    "station": "DKI09 GOR Ciracas",
    "ispu": "91",
    "parameter": "PM25",
    "tanggal": "04/30/2026 20:00:00"
  }
]