[
  {
    "timestamp": "2026-06-05T22:15:32Z",
    "timestamp_local": "2026-06-06 05:15:32",
    "station": "DKI19 Pondok Rangon",
    "ispu": "102",
    "parameter": "PM25",
    "tanggal": "06/06/2026 05:00:00"
  },
  {
    "timestamp": "2026-06-05T22:15:32Z",
    "timestamp_local": "2026-06-06 05:15:32",
    "station": "DKI16 Ancol",
    "ispu": "84",
    "parameter": "PM25",
    "tanggal": "06/06/2026 05:00:00"
  },
  {
    "timestamp": "2026-06-05T22:15:32Z",
    "timestamp_local": "2026-06-06 05:15:32",
    "station": "DKI20 Rusunawa Pesakih",
    "ispu": "94",
    "parameter": "PM25",
    "tanggal": "06/06/2026 05:00:00"
  },
  {
    "timestamp": "2026-06-05T22:15:32Z",
    "timestamp_local": "2026-06-06 05:15:32",
    "station": "DKI18 Lebak Bulus",
    "ispu": "98",
    "parameter": "PM25",
    "tanggal": "06/06/2026 05:00:00"
  },
  {
    "timestamp": "2026-06-05T22:15:32Z",
    "timestamp_local": "2026-06-06 05:15:32",
    "station": "DKI13 TMB Gombol Paya, Kalideres",
    "ispu": "109",
    "parameter": "PM25",
    "tanggal": "06/04/2026 21:00:00"
  },
  {
    "timestamp": "2026-06-05T22:15:32Z",
    "timestamp_local": "2026-06-06 05:15:32",
    "station": "DKI06 RPTRA Manggala Bisma, Papanggo",
    "ispu": "63",
    "parameter": "PM10",
    "tanggal": "06/04/2026 21:00:00"
  },
  {
    "timestamp": "2026-06-05T22:15:32Z",
    "timestamp_local": "2026-06-06 05:15:32",
    "station": "DKI95 Tebet Eco Park",
    "ispu": "89",
    "parameter": "PM25",
    "tanggal": "06/06/2026 05:00:00"
  },
  {
    "timestamp": "2026-06-05T22:15:32Z",
    "timestamp_local": "2026-06-06 05:15:32",
    "station": "DKI96 Taman Sungai Kendal",
    "ispu": "99",
    "parameter": "PM25",
    "tanggal": "06/06/2026 05:00:00"
  }
]