[
  {
    "timestamp": "2026-04-12T17:15:42Z",
    "timestamp_local": "2026-04-13 00:15:42",
    "station": "DKI19 Pondok Rangon",
    "ispu": "58",
    "parameter": "PM25",
    "tanggal": "04/13/2026 00:00:00"
  },
  {
    "timestamp": "2026-04-12T17:15:42Z",
    "timestamp_local": "2026-04-13 00:15:42",
    "station": "DKI16 Ancol",
    "ispu": "48",
    "parameter": "PM25",
    "tanggal": "04/13/2026 00:00:00"
  },
  {
    "timestamp": "2026-04-12T17:15:42Z",
    "timestamp_local": "2026-04-13 00:15:42",
    "station": "DKI17 SDN 07 Kramat Pela",
    "ispu": "58",
    "parameter": "PM25",
    "tanggal": "04/13/2026 00:00:00"
  },
  {
    "timestamp": "2026-04-12T17:15:42Z",
    "timestamp_local": "2026-04-13 00:15:42",
    "station": "DKI20 Rusunawa Pesakih",
    "ispu": "61",
    "parameter": "PM25",
    "tanggal": "04/13/2026 00:00:00"
  },
  {
    "timestamp": "2026-04-12T17:15:42Z",
    "timestamp_local": "2026-04-13 00:15:42",
    "station": "DKI13 TMB Gombol Paya, Kalideres",
    "ispu": "56",
    "parameter": "PM25",
    "tanggal": "03/26/2026 19:30:00"
  },
  {
    "timestamp": "2026-04-12T17:15:42Z",
    "timestamp_local": "2026-04-13 00:15:42",
    "station": "DKI06 RPTRA Manggala Bisma, Papanggo",
    "ispu": "110",
    "parameter": "SO2",
    "tanggal": "04/02/2026 10:00:00"
  },
  {
    "timestamp": "2026-04-12T17:15:42Z",
    "timestamp_local": "2026-04-13 00:15:42",
    "station": "DKI95 Tebet Eco Park",
    "ispu": "45",
    "parameter": "PM25",
    "tanggal": "04/13/2026 00:00:00"
  },
  {
    "timestamp": "2026-04-12T17:15:42Z",
    "timestamp_local": "2026-04-13 00:15:42",
    "station": "DKI96 Taman Sungai Kendal",
    "ispu": "60",
    "parameter": "PM25",
    "tanggal": "04/13/2026 00:00:00"
  }
]